yaqd_attune/VERSION
yaqd_attune/__init__.py
yaqd_attune/__version__.py
yaqd_attune/_attune.py
yaqd_attune/_attune_delay.py
yaqd_attune/attune-delay.avpr
yaqd_attune/attune-delay.toml
yaqd_attune/attune.avpr
yaqd_attune/attune.toml
yaqd_attune/gui/__init__.py
yaqd_attune/gui/_attune_delay_gui.py
yaqd_attune/gui/_attune_gui.py
yaqd_attune-2022.7.0.dist-info/entry_points.txt
yaqd_attune-2022.7.0.dist-info/LICENSE
yaqd_attune-2022.7.0.dist-info/WHEEL
yaqd_attune-2022.7.0.dist-info/METADATA
yaqd_attune-2022.7.0.dist-info/RECORD
