Metadata-Version: 2.1
Name: yaqd-attune
Version: 2022.7.0
Summary: yaq daemon for attune instruments.
Home-page: https://yaq.fyi
Author: yaq developers
Requires-Python: >=3.7
Classifier: Development Status :: 2 - Pre-Alpha
Classifier: Intended Audience :: Science/Research
Classifier: License :: OSI Approved :: MIT License
Classifier: Natural Language :: English
Classifier: Programming Language :: Python :: 3
Classifier: Programming Language :: Python :: 3.7
Classifier: Programming Language :: Python :: 3.8
Classifier: Topic :: Scientific/Engineering
Requires-Dist: attune
Requires-Dist: yaqd-core>=2020.10.1
Requires-Dist: yaqc
Requires-Dist: black ; extra == "dev"
Requires-Dist: pre-commit ; extra == "dev"
Project-URL: Issues, https://github.com/yaq-project/yaqd-attune/issues
Project-URL: Source, https://github.com/yaq-project/yaqd-attune
Provides-Extra: dev
